{
  "rules": {
    ".read": false,
    ".write": false,
    "properties": {
      ".read": "auth != null && auth.provider !== 'anonymous' && auth.token.role === 'admin'",
      "property_001": {
        ".read": "auth != null && auth.provider !== 'anonymous' && (auth.token.role === 'admin' || root.child('properties/property_001/members').child(auth.uid).exists())",
        "rooms": {
          "room_001": {
            "latest": {
              ".write": "auth != null && auth.provider === 'anonymous'"
            },
            "devices": {
              ".read": "auth != null && auth.provider === 'anonymous'",
              ".write": "auth != null && auth.provider !== 'anonymous' && (auth.token.role === 'admin' || root.child('properties/property_001/members').child(auth.uid).exists())"
            },
            "settings": {
              "automationEnabled": {
                ".write": "auth != null && auth.provider !== 'anonymous' && (auth.token.role === 'admin' || root.child('properties/property_001/members').child(auth.uid).exists())",
                ".validate": "newData.isBoolean()"
              }
            }
          }
        },
        "history": {
          ".write": "auth != null && auth.provider === 'anonymous'"
        },
        "energyHistory": {
          "$roomId": {
            ".indexOn": "sampledAt"
          }
        }
      },
      "$propertyId": {
        ".read": "auth != null && auth.provider !== 'anonymous' && (auth.token.role === 'admin' || root.child('properties').child($propertyId).child('members').child(auth.uid).exists())",
        "rooms": {
          "$roomId": {
            "devices": {
              ".write": "auth != null && auth.provider !== 'anonymous' && (auth.token.role === 'admin' || root.child('properties').child($propertyId).child('members').child(auth.uid).exists())"
            },
            "settings": {
              "automationEnabled": {
                ".write": "auth != null && auth.provider !== 'anonymous' && (auth.token.role === 'admin' || root.child('properties').child($propertyId).child('members').child(auth.uid).exists())",
                ".validate": "newData.isBoolean()"
              }
            }
          }
        },
        "energyHistory": {
          "$roomId": {
            ".indexOn": "sampledAt"
          }
        }
      }
    },
    "users": {
      "$uid": {
        ".read": "auth != null && auth.uid === $uid"
      }
    }
  }
}
